open_dubbing/__init__.py
open_dubbing/audio_processing.py
open_dubbing/command_line.py
open_dubbing/coqui.py
open_dubbing/demucs.py
open_dubbing/dubbing.py
open_dubbing/exit_code.py
open_dubbing/ffmpeg.py
open_dubbing/main.py
open_dubbing/preprocessing.py
open_dubbing/pydub_audio_segment.py
open_dubbing/speech_to_text.py
open_dubbing/speech_to_text_faster_whisper.py
open_dubbing/speech_to_text_whisper_transformers.py
open_dubbing/subtitles.py
open_dubbing/text_to_speech.py
open_dubbing/text_to_speech_api.py
open_dubbing/text_to_speech_cli.py
open_dubbing/text_to_speech_coqui.py
open_dubbing/text_to_speech_edge.py
open_dubbing/text_to_speech_mms.py
open_dubbing/text_to_speech_openai.py
open_dubbing/translation.py
open_dubbing/translation_apertium.py
open_dubbing/translation_nllb.py
open_dubbing/utterance.py
open_dubbing/video_processing.py
open_dubbing/voice_gender_classifier.py
open_dubbing-0.2.3.dist-info/licenses/LICENSE
open_dubbing-0.2.3.dist-info/METADATA
open_dubbing-0.2.3.dist-info/WHEEL
open_dubbing-0.2.3.dist-info/entry_points.txt
open_dubbing-0.2.3.dist-info/top_level.txt
open_dubbing-0.2.3.dist-info/RECORD
