Metadata-Version: 2.4
Name: open-dubbing
Version: 0.2.3
Summary: AI dubbing system which uses machine learning models to automatically translate and synchronize audio dialogue into different languages.
Home-page: https://github.com/Softcatala/open-dubbing
Author: Jordi Mas
Author-email: jmas@softcatala.org
License: Apache Software License 2.0
Classifier: License :: OSI Approved :: Apache Software License
Classifier: Programming Language :: Python :: 3.11
Classifier: Programming Language :: Python :: 3.12
Classifier: Programming Language :: Python :: 3.13
Classifier: Topic :: Scientific/Engineering :: Artificial Intelligence
Requires-Python: >=3.10
License-File: LICENSE
Requires-Dist: numpy>=1.17.3
Requires-Dist: moviepy==2.2.1
Requires-Dist: demucs==4.0.1
Requires-Dist: psutil==6.0.0
Requires-Dist: torch<2.7.1,>=2.0.0
Requires-Dist: pyannote.audio==3.3.2
Requires-Dist: ctranslate2<=4.6.0,>=4.1.0
Requires-Dist: faster-whisper==1.1.1
Requires-Dist: transformers<=4.45.2,>=4.40
Requires-Dist: iso639-lang==2.3.0
Requires-Dist: edge-tts==6.1.12
Requires-Dist: audioop-lts; python_version >= "3.13"
Provides-Extra: dev
Requires-Dist: flake8==7.*; extra == "dev"
Requires-Dist: black==24.*; extra == "dev"
Requires-Dist: pytest==8.*; extra == "dev"
Requires-Dist: isort==5.13; extra == "dev"
Provides-Extra: coqui
Requires-Dist: coqui-tts>=0.25.1; extra == "coqui"
Provides-Extra: openai
Requires-Dist: openai==1.59.3; extra == "openai"
Dynamic: author
Dynamic: author-email
Dynamic: classifier
Dynamic: description
Dynamic: description-content-type
Dynamic: home-page
Dynamic: license
Dynamic: license-file
Dynamic: provides-extra
Dynamic: requires-dist
Dynamic: requires-python
Dynamic: summary
